pytest_playwright_async/__init__.py
pytest_playwright_async/__version__.py
pytest_playwright_async/pytest_playwright_async.py
pytest_playwright_async-1.1.0.dist-info/METADATA
pytest_playwright_async-1.1.0.dist-info/WHEEL
pytest_playwright_async-1.1.0.dist-info/entry_points.txt
pytest_playwright_async-1.1.0.dist-info/top_level.txt
pytest_playwright_async-1.1.0.dist-info/RECORD
