Metadata-Version: 2.1
Name: pytest_playwright_async
Version: 1.1.0
Summary: ASYNC Pytest plugin for Playwright
License: MIT
Project-URL: Homepage, https://github.com/m9810223/playwright-async-pytest
Project-URL: Source, https://github.com/m9810223/playwright-async-pytest
Requires-Python: >=3.8
Requires-Dist: pytest-playwright>=0.5.2
